[
  {
    "_id": "adf141b0-c366-11e8-9693-c73a4bbbdd00",
    "_type": "visualization",
    "_source": {
      "title": "cloudtrails: ST - eventName",
      "visState": "{\"title\":\"cloudtrails: ST - eventName\",\"type\":\"table\",\"params\":{\"perPage\":25,\"showPartialRows\":false,\"showMeticsAtAllLevels\":false,\"sort\":{\"columnIndex\":null,\"direction\":null},\"showTotal\":false,\"totalFunc\":\"sum\"},\"aggs\":[{\"id\":\"1\",\"enabled\":true,\"type\":\"count\",\"schema\":\"metric\",\"params\":{}},{\"id\":\"2\",\"enabled\":true,\"type\":\"terms\",\"schema\":\"bucket\",\"params\":{\"field\":\"eventType.keyword\",\"otherBucket\":false,\"otherBucketLabel\":\"Other\",\"missingBucket\":false,\"missingBucketLabel\":\"Missing\",\"size\":100,\"order\":\"desc\",\"orderBy\":\"1\"}},{\"id\":\"3\",\"enabled\":true,\"type\":\"significant_terms\",\"schema\":\"bucket\",\"params\":{\"field\":\"eventName.keyword\",\"size\":100}}]}",
      "uiStateJSON": "{\"vis\":{\"params\":{\"sort\":{\"columnIndex\":2,\"direction\":\"asc\"}}}}",
      "description": "",
      "version": 1,
      "kibanaSavedObjectMeta": {
        "searchSourceJSON": "{\"index\":\"5bb02b10-c342-11e8-9693-c73a4bbbdd00\",\"filter\":[],\"query\":{\"query\":\"\",\"language\":\"lucene\"}}"
      }
    }
  }
]